Metadata-Version: 2.1
Name: pathimp
Version: 1.4.0
Summary: Import Python modules from any file system path.
Home-page: http://github.com/danijar/pathimp
Author: Danijar Hafner
Author-email: mail@danijar.com
License: UNKNOWN
Platform: UNKNOWN
Classifier: License :: OSI Approved :: MIT License
Classifier: Programming Language :: Python :: 3
